omero_autotag/__init__.py
omero_autotag/apps.py
omero_autotag/urls.py
omero_autotag/utils.py
omero_autotag/views.py
omero_autotag/static/omero_autotag/js/bundle.js
omero_autotag/static/omero_autotag/js/bundle.js.LICENSE.txt
omero_autotag/static/omero_autotag/js/bundle.min.js
omero_autotag/static/omero_autotag/js/bundle.min.js.LICENSE.txt
omero_autotag/templates/omero_autotag/auto_tag_init.js.html
omero_autotag-4.3.0.dist-info/licenses/LICENSE.txt
omero_autotag-4.3.0.dist-info/METADATA
omero_autotag-4.3.0.dist-info/WHEEL
omero_autotag-4.3.0.dist-info/top_level.txt
omero_autotag-4.3.0.dist-info/RECORD
