Metadata-Version: 2.4
Name: omero-autotag
Version: 4.3.0
Summary: OMERO webtagging autotag app
Home-page: https://github.com/German-BioImaging/omero-autotag
Download-URL: https://github.com/German-BioImaging/omero-autotag/archive/v4.3.0.tar.gz
Author: D.P.W. Russell
Author-email: dpwrussell@gmail.com
Maintainer: Tom Boissonnet
Maintainer-email: tom.boissonnet@hhu.de
License: AGPL-3.0
Keywords: OMERO.web,webtagging,autotag
Classifier: Development Status :: 5 - Production/Stable
Classifier: Environment :: Web Environment
Classifier: Framework :: Django
Classifier: Intended Audience :: End Users/Desktop
Classifier: Intended Audience :: Science/Research
Classifier: License :: OSI Approved :: GNU Affero General Public License v3
Classifier: Natural Language :: English
Classifier: Operating System :: OS Independent
Classifier: Programming Language :: JavaScript
Classifier: Programming Language :: Python :: 3
Classifier: Topic :: Internet :: WWW/HTTP
Classifier: Topic :: Internet :: WWW/HTTP :: Dynamic Content
Classifier: Topic :: Internet :: WWW/HTTP :: WSGI
Classifier: Topic :: Scientific/Engineering :: Visualization
Classifier: Topic :: Software Development :: Libraries :: Application Frameworks
Classifier: Topic :: Text Processing :: Markup :: HTML
Obsoletes: omero_webtagging_autotag
Requires-Python: >=3
License-File: LICENSE.txt
Requires-Dist: omero-web>=5.21.0
Dynamic: author
Dynamic: author-email
Dynamic: classifier
Dynamic: description
Dynamic: download-url
Dynamic: home-page
Dynamic: keywords
Dynamic: license
Dynamic: license-file
Dynamic: maintainer
Dynamic: maintainer-email
Dynamic: obsoletes
Dynamic: requires-dist
Dynamic: requires-python
Dynamic: summary
